sphinx_code_tabs/__init__.py
sphinx_code_tabs/code-tabs.css
sphinx_code_tabs/code-tabs.js
sphinx_code_tabs/tabenv.sty
sphinx_code_tabs-0.5.5.dist-info/METADATA
sphinx_code_tabs-0.5.5.dist-info/UNLICENSE
sphinx_code_tabs-0.5.5.dist-info/WHEEL
sphinx_code_tabs-0.5.5.dist-info/top_level.txt
sphinx_code_tabs-0.5.5.dist-info/RECORD
