Metadata-Version: 2.1
Name: sphinx-code-tabs
Version: 0.5.5
Summary: Sphinx extension for adding alternative code-blocks as selectable tabs
Home-page: https://github.com/coldfix/sphinx-code-tabs
Download-URL: https://pypi.org/project/sphinx_code_tabs
Author: Thomas Gläßle
Author-email: thomas@coldfix.de
License: Unlicense
Project-URL: Source Code, https://github.com/coldfix/sphinx-code-tabs
Project-URL: Bug Tracker, https://github.com/coldfix/sphinx-code-tabs/issues
Project-URL: Documentation, https://sphinx-code-tabs.readthedocs.io
Keywords: sphinx extension alternative code-block tab notebook
Platform: any
Classifier: Development Status :: 4 - Beta
Classifier: Environment :: Plugins
Classifier: Intended Audience :: Developers
Classifier: License :: OSI Approved :: The Unlicense (Unlicense)
Classifier: Operating System :: OS Independent
Classifier: Programming Language :: Python :: 3
Classifier: Topic :: Documentation :: Sphinx
Requires-Python: >=3.5
Provides-Extra: doc
License-File: UNLICENSE
